[
  {
    "id": "630013807",
    "name": "ARBOR VITAE HOSPICE CARE, INC.",
    "npi": "1578831129",
    "hcaiId": "406334704",
    "businessName": "ARBOR VITAE HOSPICE CARE, INC.",
    "contactEmail": "INFO@ARBORVITAEHOSPICE.COM",
    "categoryName": "HOSPICE",
    "categoryCode": "HOSPICE",
    "licenseStatus": "ACTIVE",
    "inService": true,
    "licenseNumber": "550002435",
    "licenseEffectiveDate": "10/04/2023",
    "licenseExpirationDate": "10/03/2025",
    "dataDate": "10/18/2025",
    "capacity": 0,
    "address": "1780 TOWN AND COUNTRY DRIVE, UNIT 106",
    "city": "NORCO",
    "zip": "92860",
    "county": "RIVERSIDE",
    "phone": "(951) 735-3485",
    "lat": 33.927831,
    "lng": -117.559674
  },
  {
    "id": "630013638",
    "name": "CENTRAL CITY COMMUNITY HEALTH CENTER",
    "npi": "1033488416",
    "hcaiId": "306334643",
    "businessName": "CENTRAL CITY COMMUNITY HEALTH CENTER, INC.",
    "contactEmail": "KAREN.RODRIGUEZ@CENTRALCITYHEALTH.ORG",
    "categoryName": "PRIMARY CARE CLINIC",
    "categoryCode": "COMTYC",
    "licenseStatus": "ACTIVE",
    "inService": true,
    "licenseNumber": "550001963",
    "licenseEffectiveDate": "06/15/2025",
    "licenseExpirationDate": "06/14/2026",
    "dataDate": "10/18/2025",
    "capacity": 0,
    "address": "1860 HAMNER AVE",
    "city": "NORCO",
    "zip": "92860",
    "county": "RIVERSIDE",
    "phone": "(323) 500-3460",
    "lat": 33.90915135,
    "lng": -117.5612512
  },
  {
    "id": "630027479",
    "name": "CENTRAL CITY COMMUNITY HEALTH CENTER, INC. - MOBILE 4",
    "npi": "1033488416",
    "hcaiId": null,
    "businessName": "CENTRAL CITY COMMUNITY HEALTH CENTER, INC.",
    "contactEmail": null,
    "categoryName": "PRIMARY CARE CLINIC",
    "categoryCode": "COMTYC",
    "licenseStatus": "ACTIVE",
    "inService": true,
    "licenseNumber": "550001963",
    "licenseEffectiveDate": "06/15/2025",
    "licenseExpirationDate": "06/14/2026",
    "dataDate": "10/18/2025",
    "capacity": 0,
    "address": "1860 HAMNER AVE",
    "city": "NORCO",
    "zip": "92860",
    "county": "RIVERSIDE",
    "phone": null,
    "lat": 33.90917902,
    "lng": -117.562147
  },
  {
    "id": "630019881",
    "name": "DIGNIFIED HOSPICE CARE",
    "npi": "1689214173",
    "hcaiId": "406332932",
    "businessName": "DIGNIFIED HOSPICE CARE",
    "contactEmail": "ERUIZ@DIGNIFIEDHOSPICE.COM",
    "categoryName": "HOSPICE",
    "categoryCode": "HOSPICE",
    "licenseStatus": "ACTIVE",
    "inService": true,
    "licenseNumber": "550005771",
    "licenseEffectiveDate": "09/14/2024",
    "licenseExpirationDate": "09/13/2026",
    "dataDate": "10/18/2025",
    "capacity": 0,
    "address": "1700 HAMNER AVE, SUITE 212",
    "city": "NORCO",
    "zip": "92860",
    "county": "RIVERSIDE",
    "phone": "(951) 977-8666",
    "lat": 33.907401,
    "lng": -117.562023
  },
  {
    "id": "630007502",
    "name": "LEGACY HOME HEALTH CARE",
    "npi": "1063465557",
    "hcaiId": "406331353",
    "businessName": "A & T HEALTHCARE SERVICES, INC.",
    "contactEmail": "LEGACYHOMEHEALTH@YAHOO.COM",
    "categoryName": "HOME HEALTH AGENCY",
    "categoryCode": "HHA",
    "licenseStatus": "ACTIVE",
    "inService": true,
    "licenseNumber": "550000308",
    "licenseEffectiveDate": "06/28/2025",
    "licenseExpirationDate": "06/27/2026",
    "dataDate": "10/18/2025",
    "capacity": 0,
    "address": "1700 HAMNER AVE, SUITE 104",
    "city": "NORCO",
    "zip": "92860",
    "county": "RIVERSIDE",
    "phone": "(951) 479-5656",
    "lat": 33.907401,
    "lng": -117.562023
  },
  {
    "id": "250001776",
    "name": "NOREL HOUSE",
    "npi": "1346499753",
    "hcaiId": null,
    "businessName": "CASTLES CARE HOMES, INC.",
    "contactEmail": "GLOREENBVIGILANT@SBCGLOBAL.NET",
    "categoryName": "INTERMEDIATE CARE FACILITY-DD/H/N/CN/IID",
    "categoryCode": "ICFDDH",
    "licenseStatus": "ACTIVE",
    "inService": true,
    "licenseNumber": "250000776",
    "licenseEffectiveDate": "11/22/2024",
    "licenseExpirationDate": "11/21/2025",
    "dataDate": "10/18/2025",
    "capacity": 6,
    "address": "1671 EL PASO DR",
    "city": "NORCO",
    "zip": "92860",
    "county": "RIVERSIDE",
    "phone": "(951) 283-9424",
    "lat": 33.905574,
    "lng": -117.5424975
  }
]